macrometa_source_collection/__init__.py
macrometa_source_collection/client.py
macrometa_source_collection/util.py
macrometa_source_collection-1.0.5.dist-info/entry_points.txt
macrometa_source_collection-1.0.5.dist-info/WHEEL
macrometa_source_collection-1.0.5.dist-info/METADATA
macrometa_source_collection-1.0.5.dist-info/RECORD
